bj_phone_number/__init__.py
bj_phone_number/tests.py
bj_phone_number-0.0.1.dist-info/DESCRIPTION.rst
bj_phone_number-0.0.1.dist-info/METADATA
bj_phone_number-0.0.1.dist-info/RECORD
bj_phone_number-0.0.1.dist-info/WHEEL
bj_phone_number-0.0.1.dist-info/metadata.json
bj_phone_number-0.0.1.dist-info/top_level.txt
