Metadata-Version: 2.0
Name: bj-phone-number
Version: 0.0.1
Summary: A fast minimal module to validate Beninese mobile phone numbers
Home-page: https://github.com/nioperas06/bj_phone_number
Author: Junior Gantin
Author-email: nioperas06@gmail.com
License: UNKNOWN
Keywords: sample setuptools development
Platform: UNKNOWN
Classifier: Development Status :: 3 - Alpha
Classifier: Intended Audience :: Developers
Classifier: Topic :: Software Development :: Build Tools
Classifier: License :: OSI Approved :: MIT License
Classifier: Programming Language :: Python :: 3
Classifier: Programming Language :: Python :: 3.4
Classifier: Programming Language :: Python :: 3.5
Classifier: Programming Language :: Python :: 3.6
